centernet/__init__.py
centernet/object_detection.py
centernet/pose_estimation.py
centernet/version.py
centernet/model/__init__.py
centernet/model/convolution.py
centernet/model/head.py
centernet/model/hourglass.py
centernet/model/object_detection.py
centernet/model/pose_estimation.py
centernet/model/residual.py
centernet/util/__init__.py
centernet/util/image.py
tf_centernet-1.0.6.dist-info/LICENSE
tf_centernet-1.0.6.dist-info/METADATA
tf_centernet-1.0.6.dist-info/WHEEL
tf_centernet-1.0.6.dist-info/top_level.txt
tf_centernet-1.0.6.dist-info/zip-safe
tf_centernet-1.0.6.dist-info/RECORD
