Metadata-Version: 2.1
Name: tf-centernet
Version: 1.0.6
Summary: CenterNet implementation by Tensorflow 2
Home-page: https://github.com/Licht-T/tf-centernet
License: MIT
Keywords: centernet,tensorflow
Platform: UNKNOWN
Classifier: Topic :: Scientific/Engineering :: Image Recognition
Classifier: License :: OSI Approved :: MIT License
Classifier: Programming Language :: Python :: 3
Requires-Dist: pillow
Requires-Dist: tensorflow
Requires-Dist: numpy
